{
  "version": "7",
  "dialect": "postgresql",
  "entries": [
    {
      "idx": 0,
      "version": "7",
      "when": 1750773248806,
      "tag": "0000_red_wiccan",
      "breakpoints": true
    },
    {
      "idx": 1,
      "version": "7",
      "when": 1750866386366,
      "tag": "0001_dry_lizard",
      "breakpoints": true
    },
    {
      "idx": 2,
      "version": "7",
      "when": 1751150360153,
      "tag": "0002_pretty_thunderball",
      "breakpoints": true
    },
    {
      "idx": 3,
      "version": "7",
      "when": 1751199910727,
      "tag": "0003_high_celestials",
      "breakpoints": true
    }
  ]
}